langsmith/__init__.py
langsmith/_expect.py
langsmith/anonymizer.py
langsmith/async_client.py
langsmith/client.py
langsmith/middleware.py
langsmith/py.typed
langsmith/pytest_plugin.py
langsmith/run_helpers.py
langsmith/run_trees.py
langsmith/schemas.py
langsmith/utils.py
langsmith/_internal/__init__.py
langsmith/_internal/_aiter.py
langsmith/_internal/_background_thread.py
langsmith/_internal/_beta_decorator.py
langsmith/_internal/_compressed_traces.py
langsmith/_internal/_constants.py
langsmith/_internal/_edit_distance.py
langsmith/_internal/_embedding_distance.py
langsmith/_internal/_multipart.py
langsmith/_internal/_operations.py
langsmith/_internal/_orjson.py
langsmith/_internal/_patch.py
langsmith/_internal/_serde.py
langsmith/_internal/otel/_otel_client.py
langsmith/_internal/otel/_otel_exporter.py
langsmith/beta/__init__.py
langsmith/beta/_evals.py
langsmith/cli/README.md
langsmith/env/__init__.py
langsmith/env/_git.py
langsmith/env/_runtime_env.py
langsmith/evaluation/__init__.py
langsmith/evaluation/_arunner.py
langsmith/evaluation/_name_generation.py
langsmith/evaluation/_runner.py
langsmith/evaluation/evaluator.py
langsmith/evaluation/llm_evaluator.py
langsmith/evaluation/string_evaluator.py
langsmith/evaluation/integrations/__init__.py
langsmith/evaluation/integrations/_langchain.py
langsmith/evaluation/integrations/test.excalidraw.png
langsmith/testing/__init__.py
langsmith/testing/_internal.py
langsmith/wrappers/__init__.py
langsmith/wrappers/_agent_utils.py
langsmith/wrappers/_anthropic.py
langsmith/wrappers/_openai.py
langsmith/wrappers/_openai_agents.py
langsmith_aipy-0.3.18.1.dist-info/METADATA
langsmith_aipy-0.3.18.1.dist-info/WHEEL
langsmith_aipy-0.3.18.1.dist-info/top_level.txt
langsmith_aipy-0.3.18.1.dist-info/RECORD
